pdistributions.py
DemystiPy/__init__.py
DemystiPy/pdistributions.py
src/__init__.py
src/DemystiPy/__init__.py
src/DemystiPy/pdistributions.py
DemystiPy-1.0.6.dist-info/LICENSE
DemystiPy-1.0.6.dist-info/METADATA
DemystiPy-1.0.6.dist-info/WHEEL
DemystiPy-1.0.6.dist-info/top_level.txt
DemystiPy-1.0.6.dist-info/RECORD
