Metadata-Version: 2.1
Name: DemystiPy
Version: 1.0.6
Summary: An approach towards explainable statistics and machine learning
Home-page: UNKNOWN
Author: Quadeer Shaikh
Author-email: quadeershaikh15.8@gmail.com
License: UNKNOWN
Platform: UNKNOWN
Classifier: Programming Language :: Python :: 3
Classifier: License :: OSI Approved :: MIT License
Classifier: Operating System :: OS Independent
Requires-Python: >=3.6
Requires-Dist: scipy
Requires-Dist: numpy
Requires-Dist: matplotlib
